codelighthouse/CodeLighthouse.py
codelighthouse/CodeLighthouseWebHandler.py
codelighthouse/__init__.py
CodeLighthouse-1.3.0.dist-info/LICENSE
CodeLighthouse-1.3.0.dist-info/METADATA
CodeLighthouse-1.3.0.dist-info/WHEEL
CodeLighthouse-1.3.0.dist-info/top_level.txt
CodeLighthouse-1.3.0.dist-info/RECORD
