Metadata-Version: 2.1
Name: CodeLighthouse
Version: 1.3.0
Summary: The python SDK for CodeLighthouse
Home-page: https://github.com/CodeLighthouse/sdk-python
Author: CodeLighthouse
Author-email: hello@codelighthouse.io
License: MIT
Platform: UNKNOWN
Requires-Python: >=3.6
Requires-Dist: requests
